baiToVoice/__init__.py
baiToVoice/baidu_ai_voice.py
baiToVoice/base.py
baiToVoice/speech.py
baiToVoice-1.2.2.dist-info/METADATA
baiToVoice-1.2.2.dist-info/RECORD
baiToVoice-1.2.2.dist-info/WHEEL
baiToVoice-1.2.2.dist-info/top_level.txt
