Metadata-Version: 2.1
Name: baiToVoice
Version: 1.2.2
Summary: 基于百度语音合成开发的，可以更加简单的使用百度语音合成的，生成你需要的语音mp3文件或者二进制数据
Home-page: https://github.com/Cendeal/baiToVoice
Author: Cendeal
Author-email: 1798062051@qq.com
License: MIT
Keywords: baidu-aip 语音合成 百度语音 baiToVoice
Platform: UNKNOWN
Classifier: Programming Language :: Python :: 3
Classifier: License :: OSI Approved :: MIT License
Requires-Dist: requests
